tradestation/__init__.py
tradestation/account.py
tradestation/oauth.py
tradestation/py.typed
tradestation/session.py
tradestation/utils.py
tradestation-0.2.dist-info/METADATA
tradestation-0.2.dist-info/WHEEL
tradestation-0.2.dist-info/licenses/LICENSE
tradestation-0.2.dist-info/RECORD
