Metadata-Version: 2.4
Name: tradestation
Version: 0.2
Summary: An unofficial, sync/async SDK for Tradestation!
Project-URL: Homepage, https://github.com/tastyware/tradestation
Project-URL: Documentation, https://tradestation.readthedocs.io/en/latest
Author-email: Graeme Holliday <graeme@tastyware.dev>, Ethan Corgatelli <ethan@tastyware.dev>
License: MIT License
License-File: LICENSE
Requires-Python: >=3.10
Requires-Dist: httpx>=0.27.2
Requires-Dist: pydantic>=2.9.2
Requires-Dist: pyjwt>=2.10.1
